revived/__init__.py
revived/action.py
revived/reducer.py
revived/store.py
revived-0.1.4.dist-info/DESCRIPTION.rst
revived-0.1.4.dist-info/METADATA
revived-0.1.4.dist-info/RECORD
revived-0.1.4.dist-info/WHEEL
revived-0.1.4.dist-info/metadata.json
revived-0.1.4.dist-info/top_level.txt
