Metadata-Version: 2.0
Name: revived
Version: 0.1.4
Summary: Redux-inspired library in python
Home-page: https://github.com/RookieGameDevs/revived
Author: Lorenzo Berni
Author-email: lorenzo@rookiegamedevs.io
License: BSD
Keywords: state store redux
Platform: UNKNOWN
Classifier: Development Status :: 5 - Production/Stable
Classifier: Intended Audience :: Developers
Classifier: Topic :: Software Development :: Libraries
Classifier: License :: OSI Approved :: BSD License
Classifier: Programming Language :: Python :: 3
Classifier: Programming Language :: Python :: 3.5
Classifier: Programming Language :: Python :: 3.6
Provides-Extra: dev
Provides-Extra: test
Requires-Dist: pytest; extra == 'test'
